rollingcv/__init__.py
rollingcv/splitter.py
rollingcv-1.0.0.dist-info/licenses/LICENSE
rollingcv-1.0.0.dist-info/METADATA
rollingcv-1.0.0.dist-info/WHEEL
rollingcv-1.0.0.dist-info/top_level.txt
rollingcv-1.0.0.dist-info/RECORD
