Metadata-Version: 2.4
Name: rollingcv
Version: 1.0.0
Summary: Fixed-window cross-validation for time series (scikit-learn compatible)
Home-page: https://github.com/marianotir/rollingcv
Author: Mariano Tir
Author-email: marianotir98@gmail.com
License: MIT
Project-URL: Homepage, https://github.com/marianotir/rollingcv
Requires-Python: >=3.7
License-File: LICENSE
Requires-Dist: numpy<2.0,>=1.18.0
Requires-Dist: scikit-learn>=0.24
Dynamic: author-email
Dynamic: home-page
Dynamic: license-file
Dynamic: requires-python
